taskbot/__init__.py
taskbot-0.0.1.dist-info/METADATA
taskbot-0.0.1.dist-info/RECORD
taskbot-0.0.1.dist-info/WHEEL
taskbot-0.0.1.dist-info/top_level.txt
