Metadata-Version: 2.1
Name: taskbot
Version: 0.0.1
Summary: a task oriented chatbot framework
Home-page: https://github.com/EvilPsyCHo/TaskBot
Author: Zhirui Zhou
Author-email: evilpsycho42@gmail.com
License: UNKNOWN
Platform: UNKNOWN
Classifier: Development Status :: 1 - Planning
Classifier: Programming Language :: Python :: 3.6
Classifier: License :: OSI Approved :: GNU General Public License v3 (GPLv3)
Classifier: Operating System :: MacOS
Classifier: Operating System :: POSIX :: Linux
